Workbook
Name AppliedDiscount: 'Order Info'!$C$22
Name MOQ: 'Order Info'!$C$17
Name FullDiscount: 'Order Info'!$C$18

Sheet Order Info
B2: LESS AND ROMANCE
B3: Wholesale Order Form — Spring/Summer 2026
B4: Currency: EUR • Prices net of VAT
B6: Buyer / Boutique
B7: Contact name
B8: Email
B9: Phone
B10: Shipping address
B11: VAT / Tax ID
B12: Preferred delivery date
B13: Payment terms
B14: Notes
B16: PRICING TIER
B17: Minimum Order Quantity (MOQ) | C17: 10000 | D17: Wholesale subtotal threshold for full discount
B18: Full discount (MOQ met) | C18: 0.5 | D18: Applied to retail when order ≥ MOQ
B19: Reduced discount (below MOQ) | C19: 0.225 | D19: Applied when order < MOQ (range 20–25%)
B21: Qualifying subtotal (@ full discount) | C21: =SUMPRODUCT('Order Form'!I2:I117,'Order Form'!F2:F117)*$C$18
B22: → Applied discount rate | C22: =IF(C21>=C17,C18,C19)
B23: → MOQ status | C23: =IF(C21>=C17,"MOQ MET — full discount applied","BELOW MOQ — reduced discount applied")
B25: ORDER TOTALS
B26: Total units | C26: =SUM('Order Form'!I2:I117)
B27: Subtotal at retail (EUR) | C27: =SUMPRODUCT('Order Form'!I2:I117,'Order Form'!F2:F117)
B28: Wholesale subtotal (EUR) | C28: =SUM('Order Form'!J2:J117)
B29: Effective discount off retail | C29: =C22
B30: Amount above / below MOQ | C30: =SUM('Order Form'!J2:J117)-C17

Sheet Order Form
A1: # | B1: Style | C1: Color | D1: Size | E1: SKU | F1: Retail (EUR) | G1: Wholesale (EUR) | H1: Stock | I1: Qty | J1: Line total (EUR)
A2: 1 | B2: SOFT LOUNGE KIMONO | C2: Bitter Coffee | D2: STANDART | E2: 47422073733220 | F2: 95 | G2: =F2*(1-AppliedDiscount) | H2: 112 | I2: 0 | J2: =I2*G2
A3: 2 | B3: SOFT LOUNGE TEE | C3: Black | D3: XS | E3: 47420784377956 | F3: 65 | G3: =F3*(1-AppliedDiscount) | H3: 10 | I3: 0 | J3: =I3*G3
A4: 3 | B4: SOFT LOUNGE TEE | C4: Butter Yellow | D4: XS | E4: 47420780085348 | F4: 65 | G4: =F4*(1-AppliedDiscount) | H4: 6 | I4: 0 | J4: =I4*G4
A5: 4 | B5: SOFT LOUNGE TEE | C5: Baby Blue | D5: XS | E5: 47420772843620 | F5: 65 | G5: =F5*(1-AppliedDiscount) | H5: 29 | I5: 0 | J5: =I5*G5
A6: 4 | B6: SOFT LOUNGE TEE | C6: Baby Blue | D6: S | E6: 47420773466212 | F6: 65 | G6: =F6*(1-AppliedDiscount) | H6: 7 | I6: 0 | J6: =I6*G6
A7: 5 | B7: SOFT LOUNGE TEE | C7: Grey Melange | D7: XS | E7: 47420724904036 | F7: 65 | G7: =F7*(1-AppliedDiscount) | H7: 16 | I7: 0 | J7: =I7*G7
A8: 5 | B8: SOFT LOUNGE TEE | C8: Grey Melange | D8: S | E8: 47420725526628 | F8: 65 | G8: =F8*(1-AppliedDiscount) | H8: 4 | I8: 0 | J8: =I8*G8
A9: 6 | B9: SOFT LOUNGE TEE | C9: Red | D9: XS | E9: 47420699344996 | F9: 65 | G9: =F9*(1-AppliedDiscount) | H9: 29 | I9: 0 | J9: =I9*G9
A10: 6 | B10: SOFT LOUNGE TEE | C10: Red | D10: S | E10: 47420699967588 | F10: 65 | G10: =F10*(1-AppliedDiscount) | H10: 7 | I10: 0 | J10: =I10*G10
A11: 7 | B11: SOFT LOUNGE TEE | C11: Stone | D11: XS | E11: 47420656746596 | F11: 65 | G11: =F11*(1-AppliedDiscount) | H11: 34 | I11: 0 | J11: =I11*G11
A12: 7 | B12: SOFT LOUNGE TEE | C12: Stone | D12: S | E12: 47420657369188 | F12: 65 | G12: =F12*(1-AppliedDiscount) | H12: 9 | I12: 0 | J12: =I12*G12
A13: 8 | B13: SOFT LOUNGE LONG TEE | C13: White | D13: XS | E13: 47420623126628 | F13: 65 | G13: =F13*(1-AppliedDiscount) | H13: 38 | I13: 0 | J13: =I13*G13
... A117: 45 | B117: SOFT ESSENTIAL TOP | C117: red | D117: L | E117: SK51525787 | F117: 55 | G117: =F117*(1-AppliedDiscount) | H117: 93 | I117: 0 | J117: =I117*G117
H119: TOTALS | I119: =SUM(I2:I117) | J119: =SUM(J2:J117)
B120: MOQ €10,000 wholesale subtotal. Below MOQ, discount drops to 20–25% off retail (see Order Info).

Sheet Style Summary
A1: Style | B1: Color | C1: Variants | D1: Sizes available | E1: Retail EUR (range) | F1: Total stock
A2: SOFT ESSENTIAL TOP | B2: Aci Kahve 1 | C2: 4 | D2: XS, S, M, L | E2: 55.00 | F2: 201
A3: SOFT ESSENTIAL TOP | B3: Baby Blue | C3: 4 | D3: XS, S, M, L | E3: 55.00 | F3: 184
A4: SOFT ESSENTIAL TOP | B4: Black | C4: 4 | D4: XS, S, M, L | E4: 55.00 | F4: 206
A5: SOFT ESSENTIAL TOP | B5: Burgundy | C5: 4 | D5: XS, S, M, L | E5: 55.00 | F5: 221
A6: SOFT ESSENTIAL TOP | B6: Butter Yellow | C6: 4 | D6: XS, S, M, L | E6: 55.00 | F6: 403
A7: SOFT ESSENTIAL TOP | B7: Grey Melange | C7: 4 | D7: XS, S, M, L | E7: 55.00 | F7: 205
A8: SOFT ESSENTIAL TOP | B8: Koyu Vizon | C8: 3 | D8: XS, S, L | E8: 55.00 | F8: 76
A9: SOFT ESSENTIAL TOP | B9: Stone | C9: 4 | D9: XS, S, M, L | E9: 55.00 | F9: 242
A10: SOFT ESSENTIAL TOP | B10: ekru | C10: 4 | D10: XS, S, M, L | E10: 55.00 | F10: 160
A11: SOFT ESSENTIAL TOP | B11: red | C11: 4 | D11: XS, S, M, L | E11: 55.00 | F11: 316
A12: SOFT LOUNGE KIMONO | B12: Baby Blue | C12: 1 | D12: STANDART | E12: 95.00 | F12: 23
A13: SOFT LOUNGE KIMONO | B13: Bitter Coffee | C13: 1 | D13: STANDART | E13: 95.00 | F13: 112
... A46: SOFT LOUNGE TEE | B46: Stone | C46: 2 | D46: XS, S | E46: 65.00 | F46: 43

Sheet Terms
B1: LESS AND ROMANCE — Wholesale Terms
B3: Minimum Order Quantity (MOQ)
B4: • MOQ: €10,000 wholesale subtotal per order
B5: • Orders ≥ €10,000 receive the full 50% off retail discount
B6: • Orders below MOQ are accepted but with a reduced 20–25% off retail discount
B7: • MOQ tier is calculated automatically on the 'Order Info' tab
B9: Pricing
B10: • All prices in EUR, net of VAT
B11: • Full wholesale price = 50% off retail (when MOQ is met)
B12: • Reduced wholesale price = 20–25% off retail (when MOQ is not met)
B13: • Retail prices shown are the suggested retail price (SRP)
B15: Payment
... B30: • Instagram: @lessandromance
